mcp_protocol/__init__.py
mcp_protocol/py.typed
mcp_protocol/types.py
mcp_protocol-0.1.0.dist-info/METADATA
mcp_protocol-0.1.0.dist-info/WHEEL
mcp_protocol-0.1.0.dist-info/top_level.txt
mcp_protocol-0.1.0.dist-info/RECORD
